{"related_names_en":"Aqib","gender_ur":"مردانہ","origin_ur":"عربی","related_names_ur":"عاقب","pronunciation_ur":"عاقب","id":"2","name_en":"Aaqib","islamic_reference_ur":"","gender_en":"Male","meaning_en":"Follower, Successor, The one who comes at the end","description_en":"Aaqib is an Arabic name for boys, meaning \"follower\" or \"successor,\" often interpreted as the one who comes last or at the end. It signifies someone who follows a path or tradition.","islamic_reference_en":"","name_ur":"عاقب","pronunciation_en":"Aa-qib","is_quranic_ur":"نہیں","origin_en":"Arabic","meaning_ur":"پیروکار، جانشین، وہ جو آخر میں آئے","description_ur":"عاقب لڑکوں کے لیے ایک عربی نام ہے، جس کا مطلب ہے \"پیروکار\" یا \"جانشین\"، اکثر اس کی تعبیر اس شخص سے کی جاتی ہے جو آخر میں آتا ہے۔ یہ کسی ایسے شخص کی علامت ہے جو کسی راستے یا روایت کی پیروی کرتا ہے۔","is_quranic_en":"No"}
