{"description_ur":"عبد الحی لڑکوں کے لیے ایک مسلم نام ہے۔ اس کا مطلب ہے \"ہمیشہ زندہ رہنے والے کا بندہ\"، جو اللہ کی طرف اشارہ کرتا ہے۔","gender_en":"Male","islamic_reference_ur":"الحی اللہ کے 99 ناموں میں سے ایک ہے۔","name_en":"Abdul Hayy","islamic_reference_en":"Al-Hayy is one of the 99 names of Allah.","pronunciation_ur":"عبد الحی","pronunciation_en":"Ab-dul Hayy","meaning_ur":"ہمیشہ زندہ رہنے والے کا بندہ","gender_ur":"مردانہ","is_quranic_ur":"نہیں","related_names_en":"Abdul Hai","origin_en":"Arabic","description_en":"Abdul Hayy is a Muslim name for boys. It means \"Slave of the Ever-Living,\" referring to Allah.","related_names_ur":"عبد الحی","name_ur":"عبد الحی","origin_ur":"عربی","is_quranic_en":"No","meaning_en":"Slave of the Ever-Living","id":"2"}
