{"name_ur":"عماد","name_en":"Imad","gender_ur":"مردانہ","is_quranic_ur":"نہیں","origin_en":"Arabic","related_names_en":"Imadeddin, Emad","origin_ur":"عربی","islamic_reference_ur":"","is_quranic_en":"No","gender_en":"Male","description_en":"Imad is an Arabic name for boys that means pillar, support, and something someone relies on. It carries a meaning of strength and reliability.","pronunciation_ur":"عماد","related_names_ur":"عمادالدین، عماد","pronunciation_en":"I-mad","meaning_ur":"ستون، سہارا، اعتماد، بھروسہ","id":"2","description_ur":"عماد ایک عربی نام ہے جو لڑکوں کے لئے استعمال ہوتا ہے، اس کا مطلب ستون، سہارا اور ایسی چیز ہے جس پر کوئی بھروسہ کر سکے۔ اس نام میں مضبوطی اور قابل اعتمادی کا مفہوم پایا جاتا ہے۔","meaning_en":"Pillar, support, confidence, trust","islamic_reference_en":""}
