{"description_en":"Inaam is an Arabic name for boys meaning reward, favour or prize. It signifies a gift or bounty.","gender_en":"Male","name_en":"Inaam","origin_en":"Arabic","meaning_ur":"اجر، انعام، فضل، عطیہ","description_ur":"انعام لڑکوں کے لیے ایک عربی نام ہے جس کا مطلب ہے اجر، انعام، یا فضل۔ یہ ایک تحفہ یا بخشش کی علامت ہے۔","islamic_reference_en":"","id":"2","origin_ur":"عربی","related_names_ur":"","islamic_reference_ur":"","name_ur":"انعام","meaning_en":"Reward, favour, prize, bounty","related_names_en":"","pronunciation_ur":"انعام","is_quranic_en":"No","gender_ur":"مردانہ","is_quranic_ur":"نہیں","pronunciation_en":"In-aam"}
