{"origin_ur":"عربی","origin_en":"Arabic","related_names_ur":"رئیسہ، رئیس","meaning_en":"Leader, chief, wealthy, rich","pronunciation_en":"Ra-ees","name_ur":"رئیس","gender_ur":"مردانہ","id":"2","description_en":"Rayees is an Arabic name meaning leader, chief or wealthy person. It is a name that reflects status and respect.","description_ur":"رئیس ایک عربی نام ہے جس کا مطلب ہے رہنما، سردار، یا امیر شخص۔ یہ ایک ایسا نام ہے جو حیثیت اور احترام کی عکاسی کرتا ہے۔","is_quranic_en":"No","gender_en":"Male","is_quranic_ur":"نہیں","islamic_reference_ur":"","islamic_reference_en":"","related_names_en":"Rais, Raeesah","pronunciation_ur":"رئیس","name_en":"Rayees","meaning_ur":"سردار، قائد، امیر، دولتمند"}
